Workbook

Sheet Draw Summary
A1: DRAW REQUEST PACKAGE
A3: PROJECT INFORMATION
A4: Project Name | B4: The Madison at Riverside
A5: Property Address | B5: 2400 Riverside Drive, Detroit, MI 48207
A6: Borrower | B6: Riverside Development Partners LLC
A7: Lender | B7: First National Construction Lending
A8: Loan Number | B8: CL-2025-0847
A9: General Contractor | B9: Riverside Builders Inc
A10: Architect | B10: Hamilton Design Associates
A12: DRAW INFORMATION
A13: Draw Number | B13: 7
A14: Draw Date | B14: 2026-04-01
A15: Draw Period | B15: 2026-03-01 to 2026-03-31
A17: FINANCIAL SUMMARY
A18: Total Budget (Contract Sum to Date) | B18: ='G702'!B6
A19: Prior Draws (Previous Certificates) | B19: ='G702'!B12
A20: Current Draw Request | B20: ='G702'!B13
A21: Cumulative Funded | B21: ='G702'!B12+'G702'!B13
A22: Remaining Balance | B22: ='G702'!B14
A23: Total Retainage Held | B23: ='G702'!B10
A25: BORROWER CERTIFICATIONS
A26: 1. | B26: All work for which payment is requested has been completed in accordance with the contract documents.
A27: 2. | B27: All amounts previously paid have been applied to costs of the work as indicated.
A28: 3. | B28: Current payment requested is now due under the terms of the loan agreement.
A29: 4. | B29: No liens, claims, or encumbrances exist against the property except as previously disclosed.
A30: 5. | B30: All subcontractors and suppliers have been paid from prior draws as required.
A31: 6. | B31: The work is proceeding on schedule and within budget, or variances have been disclosed.
A33: Prepared By: | B33: 1404 Labs
A34: Date: | B34: 2026-04-01
A36: Borrower Signature: | B36: ____________________________

Sheet G702
A1: APPLICATION AND CERTIFICATE FOR PAYMENT
A2: (AIA Document G702)
A4: 1. ORIGINAL CONTRACT SUM | B4: 38500000
A5: 2. Net Change by Change Orders | B5: =SUMIF('Change Order Log'!H2:H4,"approved",'Change Order Log'!E2:E4)
A6: 3. CONTRACT SUM TO DATE (Line 1 + Line 2) | B6: =B4+B5
A7: 4. TOTAL COMPLETED & STORED TO DATE | B7: ='G703'!G28
A8: 5a. Retainage on Completed Work (10%) | B8: =('G703'!D28+'G703'!E28)*0.1
A9: 5b. Retainage on Stored Materials (10%) | B9: ='G703'!F28*0.1
A10: 5c. Total Retainage (5a + 5b) | B10: =B8+B9
A11: 6. TOTAL EARNED LESS RETAINAGE (Line 4 - Line 5c) | B11: =B7-B10
A12: 7. LESS PREVIOUS CERTIFICATES FOR PAYMENT | B12: 17842500
A13: 8. CURRENT PAYMENT DUE (Line 6 - Line 7) | B13: =B11-B12
A14: 9. BALANCE TO FINISH INCLUDING RETAINAGE (Line 3 - Line 6) | B14: =B6-B11
A16: Retainage Percentage | B16: 0.1

Sheet G703
A1: A Item No. | B1: B Description of Work | C1: C Scheduled Value | D1: D Work Completed Previous | E1: E Work Completed This Period | F1: F Materials Stored | G1: G Total Completed & Stored | H1: H % Complete | I1: I Balance to Finish
A2: HARD COSTS
A3: 02000 | B3: Site Work & Earthwork | C3: 2850000 | D3: 2850000 | E3: 0 | F3: 0 | G3: =D3+E3+F3 | H3: =IF(C3=0,0,G3/C3) | I3: =C3-G3
A4: 03000 | B4: Concrete & Foundations | C4: 5200000 | D4: 5200000 | E4: 0 | F4: 0 | G4: =D4+E4+F4 | H4: =IF(C4=0,0,G4/C4) | I4: =C4-G4
A5: 05000 | B5: Structural Steel & Metals | C5: 4100000 | D5: 3690000 | E5: 410000 | F5: 0 | G5: =D5+E5+F5 | H5: =IF(C5=0,0,G5/C5) | I5: =C5-G5
A6: 06000 | B6: Rough Carpentry & Framing | C6: 3800000 | D6: 2280000 | E6: 570000 | F6: 190000 | G6: =D6+E6+F6 | H6: =IF(C6=0,0,G6/C6) | I6: =C6-G6
A7: 07000 | B7: Thermal & Moisture Protection | C7: 2200000 | D7: 880000 | E7: 440000 | F7: 110000 | G7: =D7+E7+F7 | H7: =IF(C7=0,0,G7/C7) | I7: =C7-G7
A8: 08000 | B8: Doors, Windows & Glazing | C8: 2600000 | D8: 520000 | E8: 390000 | F8: 260000 | G8: =D8+E8+F8 | H8: =IF(C8=0,0,G8/C8) | I8: =C8-G8
A9: 09000 | B9: Finishes (Drywall, Paint, Flooring, Tile) | C9: 4500000 | D9: 450000 | E9: 675000 | F9: 225000 | G9: =D9+E9+F9 | H9: =IF(C9=0,0,G9/C9) | I9: =C9-G9
A10: 15000 | B10: Mechanical / HVAC | C10: 3400000 | D10: 1360000 | E10: 510000 | F10: 170000 | G10: =D10+E10+F10 | H10: =IF(C10=0,0,G10/C10) | I10: =C10-G10
A11: 15500 | B11: Plumbing | C11: 2100000 | D11: 1050000 | E11: 315000 | F11: 0 | G11: =D11+E11+F11 | H11: =IF(C11=0,0,G11/C11) | I11: =C11-G11
A12: 16000 | B12: Electrical | C12: 2800000 | D12: 1120000 | E12: 420000 | F12: 140000 | G12: =D12+E12+F12 | H12: =IF(C12=0,0,G12/C12) | I12: =C12-G12
A13: 23000 | B13: Fire Protection | C13: 950000 | D13: 285000 | E13: 142500 | F13: 0 | G13: =D13+E13+F13 | H13: =IF(C13=0,0,G13/C13) | I13: =C13-G13
A14: 32000 | B14: Exterior Improvements & Landscaping | C14: 1200000 | D14: 0 | E14: 0 | F14: 0 | G14: =D14+E14+F14 | H14: =IF(C14=0,0,G14/C14) | I14: =C14-G14
A15: SOFT COSTS
A16: S-01 | B16: Architecture & Engineering | C16: 1800000 | D16: 1620000 | E16: 90000 | F16: 0 | G16: =D16+E16+F16 | H16: =IF(C16=0,0,G16/C16) | I16: =C16-G16
A17: S-02 | B17: Permits & Impact Fees | C17: 950000 | D17: 950000 | E17: 0 | F17: 0 | G17: =D17+E17+F17 | H17: =IF(C17=0,0,G17/C17) | I17: =C17-G17
A18: S-03 | B18: Legal & Title | C18: 350000 | D18: 280000 | E18: 35000 | F18: 0 | G18: =D18+E18+F18 | H18: =IF(C18=0,0,G18/C18) | I18: =C18-G18
A19: S-04 | B19: Builder's Risk Insurance | C19: 425000 | D19: 297500 | E19: 42500 | F19: 0 | G19: =D19+E19+F19 | H19: =IF(C19=0,0,G19/C19) | I19: =C19-G19
A20: FINANCING COSTS
A21: F-01 | B21: Loan Origination & Fees | C21: 575000 | D21: 575000 | E21: 0 | F21: 0 | G21: =D21+E21+F21 | H21: =IF(C21=0,0,G21/C21) | I21: =C21-G21
A22: F-02 | B22: Capitalized Interest | C22: 1700000 | D22: 1020000 | E22: 121500 | F22: 0 | G22: =D22+E22+F22 | H22: =IF(C22=0,0,G22/C22) | I22: =C22-G22
B24: HARD COSTS SUBTOTAL | C24: =C3+C4+C5+C6+C7+C8+C9+C10+C11+C12+C13+C14 | D24: =D3+D4+D5+D6+D7+D8+D9+D10+D11+D12+D13+D14 | E24: =E3+E4+E5+E6+E7+E8+E9+E10+E11+E12+E13+E14 | F24: =F3+F4+F5+F6+F7+F8+F9+F10+F11+F12+F13+F14 | G24: =G3+G4+G5+G6+G7+G8+G9+G10+G11+G12+G13+G14 | H24: =IF(C24=0,0,G24/C24) | I24: =I3+I4+I5+I6+I7+I8+I9+I10+I11+I12+I13+I14
B25: SOFT COSTS SUBTOTAL | C25: =C16+C17+C18+C19 | D25: =D16+D17+D18+D19 | E25: =E16+E17+E18+E19 | F25: =F16+F17+F18+F19 | G25: =G16+G17+G18+G19 | H25: =IF(C25=0,0,G25/C25) | I25: =I16+I17+I18+I19
B26: FINANCING COSTS SUBTOTAL | C26: =C21+C22 | D26: =D21+D22 | E26: =E21+E22 | F26: =F21+F22 | G26: =G21+G22 | H26: =IF(C26=0,0,G26/C26) | I26: =I21+I22
B28: GRAND TOTAL | C28: =C24+C25+C26 | D28: =D24+D25+D26 | E28: =E24+E25+E26 | F28: =F24+F25+F26 | G28: =G24+G25+G26 | H28: =IF(C28=0,0,G28/C28) | I28: =I24+I25+I26

Sheet Change Order Log
A1: CO # | B1: Date Submitted | C1: Date Approved | D1: Description | E1: Cost Impact (Add/Deduct) | F1: Net Impact (Running) | G1: Schedule Impact (Days) | H1: Status
A2: 1 | B2: 2025-09-15 | C2: 2025-09-28 | D2: Upgraded elevator cab finishes per owner request | E2: 185000 | F2: =E2 | G2: 0 | H2: approved
A3: 2 | B3: 2025-11-02 | C3: 2025-11-18 | D3: Rock removal — unforeseen subsurface conditions at Building C | E3: 342000 | F3: =F2+E3 | G3: 12 | H3: approved
A4: 3 | B4: 2026-01-20 | C4: 2026-02-05 | D4: Structural steel reinforcement per revised wind load calcs | E4: 128000 | F4: =F3+E4 | G4: 5 | H4: approved
B6: TOTALS | E6: =SUM(E2:E4) | F6: =F4 | G6: =SUM(G2:G4)

Sheet Budget Summary
A1: Line Item | B1: Original Budget | C1: Approved COs | D1: Current Budget | E1: Prior Draws | F1: Current Draw | G1: Total Funded | H1: Remaining | I1: Projected Final Cost | J1: Variance
A2: HARD COSTS
A3: Site Work & Earthwork | B3: 2850000 | C3: 0 | D3: =B3+C3 | E3: 2850000 | F3: 0 | G3: =E3+F3 | H3: =D3-G3 | I3: =D3 | J3: =I3-D3
A4: Concrete & Foundations | B4: 5200000 | C4: 0 | D4: =B4+C4 | E4: 5200000 | F4: 0 | G4: =E4+F4 | H4: =D4-G4 | I4: =D4 | J4: =I4-D4
A5: Structural Steel & Metals | B5: 4100000 | C5: 0 | D5: =B5+C5 | E5: 3690000 | F5: 410000 | G5: =E5+F5 | H5: =D5-G5 | I5: =D5 | J5: =I5-D5
A6: Rough Carpentry & Framing | B6: 3800000 | C6: 0 | D6: =B6+C6 | E6: 2280000 | F6: 760000 | G6: =E6+F6 | H6: =D6-G6 | I6: =D6 | J6: =I6-D6
A7: Thermal & Moisture Protection | B7: 2200000 | C7: 0 | D7: =B7+C7 | E7: 880000 | F7: 550000 | G7: =E7+F7 | H7: =D7-G7 | I7: =D7 | J7: =I7-D7
A8: Doors, Windows & Glazing | B8: 2600000 | C8: 0 | D8: =B8+C8 | E8: 520000 | F8: 650000 | G8: =E8+F8 | H8: =D8-G8 | I8: =D8 | J8: =I8-D8
A9: Finishes (Drywall, Paint, Flooring, Tile) | B9: 4500000 | C9: 0 | D9: =B9+C9 | E9: 450000 | F9: 900000 | G9: =E9+F9 | H9: =D9-G9 | I9: =D9 | J9: =I9-D9
A10: Mechanical / HVAC | B10: 3400000 | C10: 0 | D10: =B10+C10 | E10: 1360000 | F10: 680000 | G10: =E10+F10 | H10: =D10-G10 | I10: =D10 | J10: =I10-D10
A11: Plumbing | B11: 2100000 | C11: 0 | D11: =B11+C11 | E11: 1050000 | F11: 315000 | G11: =E11+F11 | H11: =D11-G11 | I11: =D11 | J11: =I11-D11
A12: Electrical | B12: 2800000 | C12: 0 | D12: =B12+C12 | E12: 1120000 | F12: 560000 | G12: =E12+F12 | H12: =D12-G12 | I12: =D12 | J12: =I12-D12
A13: Fire Protection | B13: 950000 | C13: 0 | D13: =B13+C13 | E13: 285000 | F13: 142500 | G13: =E13+F13 | H13: =D13-G13 | I13: =D13 | J13: =I13-D13
A14: Exterior Improvements & Landscaping | B14: 1200000 | C14: 0 | D14: =B14+C14 | E14: 0 | F14: 0 | G14: =E14+F14 | H14: =D14-G14 | I14: =D14 | J14: =I14-D14
A15: SOFT COSTS
A16: Architecture & Engineering | B16: 1800000 | C16: 0 | D16: =B16+C16 | E16: 1620000 | F16: 90000 | G16: =E16+F16 | H16: =D16-G16 | I16: =D16 | J16: =I16-D16
A17: Permits & Impact Fees | B17: 950000 | C17: 0 | D17: =B17+C17 | E17: 950000 | F17: 0 | G17: =E17+F17 | H17: =D17-G17 | I17: =D17 | J17: =I17-D17
A18: Legal & Title | B18: 350000 | C18: 0 | D18: =B18+C18 | E18: 280000 | F18: 35000 | G18: =E18+F18 | H18: =D18-G18 | I18: =D18 | J18: =I18-D18
A19: Builder's Risk Insurance | B19: 425000 | C19: 0 | D19: =B19+C19 | E19: 297500 | F19: 42500 | G19: =E19+F19 | H19: =D19-G19 | I19: =D19 | J19: =I19-D19
A20: FINANCING COSTS
A21: Loan Origination & Fees | B21: 575000 | C21: 0 | D21: =B21+C21 | E21: 575000 | F21: 0 | G21: =E21+F21 | H21: =D21-G21 | I21: =D21 | J21: =I21-D21
A22: Capitalized Interest | B22: 1700000 | C22: 0 | D22: =B22+C22 | E22: 1020000 | F22: 121500 | G22: =E22+F22 | H22: =D22-G22 | I22: =D22 | J22: =I22-D22
A24: HARD COSTS SUBTOTAL | B24: =B3+B4+B5+B6+B7+B8+B9+B10+B11+B12+B13+B14 | C24: =C3+C4+C5+C6+C7+C8+C9+C10+C11+C12+C13+C14 | D24: =B24+C24 | E24: =E3+E4+E5+E6+E7+E8+E9+E10+E11+E12+E13+E14 | F24: =F3+F4+F5+F6+F7+F8+F9+F10+F11+F12+F13+F14 | G24: =E24+F24 | H24: =D24-G24 | I24: =I3+I4+I5+I6+I7+I8+I9+I10+I11+I12+I13+I14 | J24: =I24-D24
A25: SOFT COSTS SUBTOTAL | B25: =B16+B17+B18+B19 | C25: =C16+C17+C18+C19 | D25: =B25+C25 | E25: =E16+E17+E18+E19 | F25: =F16+F17+F18+F19 | G25: =E25+F25 | H25: =D25-G25 | I25: =I16+I17+I18+I19 | J25: =I25-D25
A26: FINANCING COSTS SUBTOTAL | B26: =B21+B22 | C26: =C21+C22 | D26: =B26+C26 | E26: =E21+E22 | F26: =F21+F22 | G26: =E26+F26 | H26: =D26-G26 | I26: =I21+I22 | J26: =I26-D26
A28: TOTAL PROJECT BUDGET | B28: =B24+B25+B26 | C28: =C24+C25+C26 | D28: =B28+C28 | E28: =E24+E25+E26 | F28: =F24+F25+F26 | G28: =E28+F28 | H28: =D28-G28 | I28: =I24+I25+I26 | J28: =I28-D28

Sheet Lien Waiver Tracker
A1: Company Name | B1: Trade | C1: Contract Amount | D1: Paid to Date | E1: Due This Draw | F1: Balance | G1: Conditional Progress | H1: Unconditional Progress | I1: Signature Date | J1: Notes
A2: Great Lakes Excavating | B2: Site Work | C2: 2850000 | D2: 2565000 | E2: 0 | F2: =C2-D2-E2 | G2: N/A | H2: Received | I2: 2026-03-05 | J2: Complete — final waiver pending retainage release
A3: Motor City Concrete | B3: Concrete | C3: 5200000 | D3: 4680000 | E3: 0 | F3: =C3-D3-E3 | G3: N/A | H3: Received | I3: 2026-03-08 | J3: Complete
A4: Ironworkers Local 25 Steel | B4: Structural Steel | C4: 4100000 | D4: 3321000 | E4: 369000 | F4: =C4-D4-E4 | G4: Received | H4: Received | I4: 2026-03-28
A5: Midwest Framing Corp | B5: Rough Carpentry | C5: 3800000 | D5: 2052000 | E5: 684000 | F5: =C5-D5-E5 | G5: Received | H5: Received | I5: 2026-03-27
A6: Barrier Systems Inc | B6: Waterproofing & Insulation | C6: 2200000 | D6: 792000 | E6: 495000 | F6: =C6-D6-E6 | G6: Received | H6: Pending | I6: 2026-03-29 | J6: Unconditional for Draw 6 still pending
A7: Wolverine Glass & Glazing | B7: Windows & Glazing | C7: 2600000 | D7: 468000 | E7: 585000 | F7: =C7-D7-E7 | G7: Received | H7: Received | I7: 2026-03-30
A8: Elite Interior Finishes | B8: Finishes | C8: 4500000 | D8: 405000 | E8: 810000 | F8: =C8-D8-E8 | G8: Pending | H8: Received | J8: Conditional waiver requested — awaiting return
A9: Comfort Mechanical | B9: HVAC | C9: 3400000 | D9: 1224000 | E9: 612000 | F9: =C9-D9-E9 | G9: Received | H9: Received | I9: 2026-03-26
A10: Allied Plumbing Services | B10: Plumbing | C10: 2100000 | D10: 945000 | E10: 283500 | F10: =C10-D10-E10 | G10: Received | H10: Received | I10: 2026-03-25
A11: PowerLine Electric | B11: Electrical | C11: 2800000 | D11: 1008000 | E11: 504000 | F11: =C11-D11-E11 | G11: Received | H11: Missing | I11: 2026-03-28 | J11: Unconditional for Draw 6 missing — follow up
A12: FireGuard Sprinkler | B12: Fire Protection | C12: 950000 | D12: 256500 | E12: 128250 | F12: =C12-D12-E12 | G12: Received | H12: Received | I12: 2026-03-24
A13: GreenScape Landscaping | B13: Landscaping | C13: 1200000 | D13: 0 | E13: 0 | F13: =C13-D13-E13 | G13: N/A | H13: N/A | J13: Not yet mobilized
A15: TOTALS | C15: =SUM(C2:C13) | D15: =SUM(D2:D13) | E15: =SUM(E2:E13) | F15: =SUM(F2:F13)
A17: COMPLIANCE SUMMARY
A18: Active Subcontractors | B18: =COUNTIF(E2:E13,">0")+COUNTIF(D2:D13,">0")-COUNTIFS(E2:E13,">0",D2:D13,">0")
A19: Conditional Waivers — Received | B19: =COUNTIF(G2:G13,"Received")
A20: Conditional Waivers — Pending | B20: =COUNTIF(G2:G13,"Pending")
A21: Conditional Waivers — Missing | B21: =COUNTIF(G2:G13,"Missing")
A22: Unconditional Waivers — Received | B22: =COUNTIF(H2:H13,"Received")
A23: Unconditional Waivers — Pending/Missing | B23: =COUNTIF(H2:H13,"Pending")+COUNTIF(H2:H13,"Missing")
A25: Conditional Compliance % | B25: =IF((COUNTIF(G2:G13,"Received")+COUNTIF(G2:G13,"Pending")+COUNTIF(G2:G13,"Missing"))=0,0,COUNTIF(G2:G13,"Received")/(COUNTIF(G2:G13,"Received")+COUNTIF(G2:G13,"Pending")+COUNTIF(G2:G13,"Missing")))
A26: Unconditional Compliance % | B26: =IF((COUNTIF(H2:H13,"Received")+COUNTIF(H2:H13,"Pending")+COUNTIF(H2:H13,"Missing"))=0,0,COUNTIF(H2:H13,"Received")/(COUNTIF(H2:H13,"Received")+COUNTIF(H2:H13,"Pending")+COUNTIF(H2:H13,"Missing")))
