Workbook
Name GLTotal: 'Reconciliation'!$C$11
Name Total1099NEC: 'Reconciliation'!$C$14
Name Total1099MISC: 'Reconciliation'!$C$15
Name TotalAccountedFor: 'Reconciliation'!$C$25
Name Variance: 'Reconciliation'!$C$26

Sheet 1099-NEC List
A1: Acme Construction LLC
A2: 1099-NEC List — Nonemployee Compensation
A3: Tax Year 2025 | Prepared January 15, 2026
A4: Prepared by 1404 Labs | Threshold: $600
A6: Vendor Name (Legal) | B6: DBA / Business Name | C6: TIN / EIN | D6: TIN Type | E6: Address | F6: City | G6: State | H6: ZIP | I6: Entity Type | J6: Total Payments | K6: Credit Card / 3rd Party | L6: Materials Only | M6: 1099 Reportable Amount | N6: 1099 Type | O6: 1099 Box | P6: W-9 on File? | Q6: W-9 Date | R6: TIN Verified? | S6: Backup W/H? | T6: Backup W/H Amt | U6: Notes
A7: Martinez Drywall LLC | C7: XXX-XX-8821 | D7: EIN | E7: 450 Industrial Blvd | F7: Dearborn | G7: MI | H7: 48124 | I7: LLC | J7: 187500 | K7: 0 | L7: 0 | M7: =J7-K7-L7 | N7: NEC | O7: Box 1 | P7: YES | Q7: 03/15/2025 | R7: YES | S7: NO | T7: 0 | U7: Largest sub — multiple projects
A8: Apex Roofing LLC | C8: XXX-XX-3366 | D8: EIN | E8: 900 Shingle Rd | F8: Novi | G8: MI | H8: 48375 | I8: LLC | J8: 112000 | K8: 0 | L8: 0 | M8: =J8-K8-L8 | N8: NEC | O8: Box 1 | P8: YES | Q8: 02/10/2025 | R8: YES | S8: NO | T8: 0
A9: Rodriguez Framing | C9: MISSING | E9: 1847 Carpenter Ave | F9: Ypsilanti | G9: MI | H9: 48197 | I9: Sole Prop | J9: 67800 | K9: 0 | L9: 0 | M9: =J9-K9-L9 | N9: NEC | O9: Box 1 | P9: NO | R9: NO | S9: NO | T9: 0 | U9: MISSING W-9 — requested 11/15, no response
A10: James Whitfield | B10: Whitfield Excavation | C10: XXX-XX-5544 | D10: SSN | E10: 3200 Dirt Rd | F10: Plymouth | G10: MI | H10: 48170 | I10: Sole Prop | J10: 73500 | K10: 0 | L10: 15000 | M10: =J10-K10-L10 | N10: NEC | O10: Box 1 | P10: YES | Q10: 04/05/2025 | R10: NO | S10: NO | T10: 0 | U10: Labor + materials — materials separated
A11: Singh HVAC Services | C11: XXX-XX-2233 | D11: EIN | E11: 4100 Cool Breeze Dr | F11: Sterling Heights | G11: MI | H11: 48310 | I11: Partnership | J11: 54300 | K11: 12000 | L11: 0 | M11: =J11-K11-L11 | N11: NEC | O11: Box 1 | P11: YES | Q11: 05/10/2025 | R11: YES | S11: NO | T11: 0 | U11: Partial credit card payments excluded
A12: Tony Ramirez | B12: Ramirez Painting | C12: XXX-XX-5567 | D12: SSN | E12: 221 Oak St | F12: Southfield | G12: MI | H12: 48075 | I12: Sole Prop | J12: 43200 | K12: 0 | L12: 8400 | M12: =J12-K12-L12 | N12: NEC | O12: Box 1 | P12: YES | Q12: 06/01/2025 | R12: NO | S12: NO | T12: 0 | U12: Labor + materials — materials separated
A13: TOTALS | B13: =COUNTA(A7:A12) | J13: =SUM(J7:J12) | K13: =SUM(K7:K12) | L13: =SUM(L7:L12) | M13: =SUM(M7:M12) | T13: =SUM(T7:T12)

Sheet 1099-MISC List
A1: Acme Construction LLC
A2: 1099-MISC List — Rents, Legal, Medical
A3: Tax Year 2025 | Prepared January 15, 2026
A4: Prepared by 1404 Labs | Threshold: $600
A6: Vendor Name (Legal) | B6: DBA / Business Name | C6: TIN / EIN | D6: TIN Type | E6: Address | F6: City | G6: State | H6: ZIP | I6: Entity Type | J6: Total Payments | K6: Credit Card / 3rd Party | L6: Materials Only | M6: 1099 Reportable Amount | N6: 1099 Type | O6: 1099 Box | P6: W-9 on File? | Q6: W-9 Date | R6: TIN Verified? | S6: Backup W/H? | T6: Backup W/H Amt | U6: Notes | V6: MISC Box Assignment
A7: Lakeside Property Management | C7: XXX-XX-4455 | D7: EIN | E7: 300 Lakeside Dr | F7: Ann Arbor | G7: MI | H7: 48103 | I7: LLC | J7: 36000 | K7: 0 | L7: 0 | M7: =J7-K7-L7 | N7: MISC | O7: Box 1 | P7: YES | Q7: 01/15/2025 | R7: YES | S7: NO | T7: 0 | U7: Yard/office rent — 1099-MISC Box 1 | V7: Box 1
A8: Hendricks & Associates PLLC | C8: XXX-XX-7788 | D8: EIN | E8: 100 W Congress St Ste 800 | F8: Detroit | G8: MI | H8: 48226 | I8: LLC | J8: 18500 | K8: 0 | L8: 0 | M8: =J8-K8-L8 | N8: MISC | O8: Box 10 | P8: YES | Q8: 01/05/2025 | R8: YES | S8: NO | T8: 0 | U8: Attorney — report even if corporation (Box 10) | V8: Box 10
A9: TOTALS | B9: =COUNTA(A7:A8) | J9: =SUM(J7:J8) | K9: =SUM(K7:K8) | L9: =SUM(L7:L8) | M9: =SUM(M7:M8) | T9: =SUM(T7:T8)

Sheet Missing W-9s
A1: Acme Construction LLC
A2: Missing W-9s — Tax Year 2025
A3: ACTION REQUIRED: Collect W-9 or apply 24% backup withholding
A5: Vendor Name | B5: Total Payments | C5: Last Payment Date | D5: Contact Info | E5: W-9 Request Sent | F5: Follow-up Needed? | G5: Backup W/H Required?
A6: Rodriguez Framing | B6: 67800 | C6: 12/10/2025 | D6: rodriguez.framing@yahoo.com | E6: 11/15/2025 | F6: VERIFY | G6: =IF(B6>=600,"YES","NO")

Sheet Excluded Vendors
A1: Acme Construction LLC
A2: Excluded Vendors — Tax Year 2025
A3: Vendors not requiring 1099 with documented exclusion reason
A5: Vendor Name | B5: Total Payments | C5: Exclusion Reason | D5: Entity Type | E5: Supporting Documentation
A6: Precision Electric Inc | B6: 142000 | C6: CORPORATION | D6: S-Corporation | E6: W-9 on file (rcvd 01/10/2025) — S-Corporation classification; S-Corp per W-9 — excluded
A7: Great Lakes Concrete Supply | B7: 95600 | C7: MATERIALS_ONLY | D7: C-Corporation | E7: Materials only: $95,600.00 of $95,600.00 total; Materials only — concrete supply
A8: ABC Plumbing Corp | B8: 88400 | C8: CORPORATION | D8: C-Corporation | E8: W-9 on file (rcvd 04/20/2025) — C-Corporation classification; C-Corp per W-9 — excluded
A9: Dan Morrison | B9: 28900 | C9: CREDIT_CARD | D9: Individual | E9: All $28,900.00 via credit card/3rd party — 1099-K from processor; All payments via credit card — 1099-K from processor
A10: Midwest Fasteners Inc | B10: 450 | C10: BELOW_THRESHOLD | D10: C-Corporation | E10: Total payments $450.00 < $600 threshold; Below $600 threshold
A11: TOTAL EXCLUDED | B11: =SUM(B6:B10)

Sheet Reconciliation
A1: Acme Construction LLC
A2: 1099 Reconciliation — Tax Year 2025
A3: Reconcile 1099 totals + exclusions to GL expense accounts
A5: Row | B5: Description | C5: Amount | D5: Source
B6: GL EXPENSE ACCOUNTS
A7: 1 | B7: 5100 — Subcontractor Expense | C7: 625000 | D7: QBO P&L — GL Account
A8: 2 | B8: 6200 — Rent Expense | C8: 36000 | D8: QBO P&L — GL Account
A9: 3 | B9: 6300 — Legal & Professional Fees | C9: 22500 | D9: QBO P&L — GL Account
A10: 4 | B10: 5200 — Materials & Supplies | C10: 164650 | D10: QBO P&L — GL Account
B11: Total GL Subcontractor/Service Expense | C11: =SUM(C7:C10) | D11: Sum of GL accounts above
B13: 1099 AMOUNTS
B14: Total 1099-NEC Amounts (Tab 1) | C14: ='1099-NEC List'!M13 | D14: SUM of Tab 1 Column M (totals row)
B15: Total 1099-MISC Amounts (Tab 2) | C15: ='1099-MISC List'!M9 | D15: SUM of Tab 2 Column M (totals row)
B17: EXCLUSIONS
B18: Excluded — Corporations | C18: =SUMIF('Excluded Vendors'!C6:C10,"CORPORATION",'Excluded Vendors'!B6:B10) | D18: From Tab 4 (CORPORATION rows)
B19: Excluded — Below Threshold | C19: =SUMIF('Excluded Vendors'!C6:C10,"BELOW_THRESHOLD",'Excluded Vendors'!B6:B10) | D19: From Tab 4 (BELOW_THRESHOLD rows)
B20: Excluded — Materials Only | C20: =SUMIF('Excluded Vendors'!C6:C10,"MATERIALS_ONLY",'Excluded Vendors'!B6:B10) | D20: From Tab 4 (MATERIALS_ONLY rows)
B21: Excluded — Credit Card / 3rd Party | C21: =SUMIF('Excluded Vendors'!C6:C10,"CREDIT_CARD",'Excluded Vendors'!B6:B10) | D21: From Tab 4 (CREDIT_CARD rows)
B22: Excluded — Employees (W-2) | C22: =SUMIF('Excluded Vendors'!C6:C10,"EMPLOYEE",'Excluded Vendors'!B6:B10) | D22: From Tab 4 (EMPLOYEE rows)
B23: Excluded — Other (Tax-Exempt, Foreign) | C23: =SUMIF('Excluded Vendors'!C6:C10,"TAX_EXEMPT",'Excluded Vendors'!B6:B10)+SUMIF('Excluded Vendors'!C6:C10,"FOREIGN",'Excluded Vendors'!B6:B10) | D23: From Tab 4 (remaining reasons)
B25: TOTAL ACCOUNTED FOR | C25: =C14+C15+C18+C19+C20+C21+C22+C23 | D25: 1099 amounts + all exclusions
B26: VARIANCE | C26: =C11-C25 | D26: GL Total - Total Accounted For
B27: Variance Acceptable? (< $100) | C27: =IF(ABS(C26)<100,"YES","NO") | D27: Must be within $100 to proceed with filing
